aiocse/__init__.py
aiocse/client.py
aiocse/errors.py
aiocse/result.py
aiocse-1.0.1.dist-info/LICENSE
aiocse-1.0.1.dist-info/METADATA
aiocse-1.0.1.dist-info/WHEEL
aiocse-1.0.1.dist-info/top_level.txt
aiocse-1.0.1.dist-info/RECORD
