Metadata-Version: 2.1
Name: aiocse
Version: 1.0.1
Summary: A Python wrapper for the Google Custom Search JSON API.
Home-page: https://github.com/Daudd/aiocse
Author: Daud
License: MIT
Platform: UNKNOWN
Requires-Dist: aiohttp
